setup.py
django_syncr.egg-info/PKG-INFO
django_syncr.egg-info/SOURCES.txt
django_syncr.egg-info/dependency_links.txt
django_syncr.egg-info/not-zip-safe
django_syncr.egg-info/top_level.txt
syncr/__init__.py
syncr/app/__init__.py
syncr/app/delicious.py
syncr/app/flickr.py
syncr/app/genericfeed.py
syncr/app/googlecode.py
syncr/app/magnolia.py
syncr/app/picasaweb.py
syncr/app/syncbk.py
syncr/app/syncreadernaut.py
syncr/app/tumblr.py
syncr/app/tweet.py
syncr/app/youtube.py
syncr/brightkite/__init__.py
syncr/brightkite/admin.py
syncr/brightkite/bk.py
syncr/brightkite/models.py
syncr/brightkite/object_dict.py
syncr/brightkite/oodict.py
syncr/brightkite/xml2dict.py
syncr/delicious/__init__.py
syncr/delicious/admin.py
syncr/delicious/models.py
syncr/doc/brightkite_README.rtf
syncr/doc/readernaut_README.rtf
syncr/doc/syncr.app.delicious.html
syncr/doc/syncr.app.flickr.html
syncr/doc/syncr.app.html
syncr/doc/syncr.app.tweet.html
syncr/doc/syncr.app.youtube.html
syncr/doc/syncr.html
syncr/flickr/__init__.py
syncr/flickr/admin.py
syncr/flickr/models.py
syncr/flickr/slug.py
syncr/flickr/views.py
syncr/flickr/templatetags/__init__.py
syncr/flickr/templatetags/flickr.py
syncr/genericfeed/__init__.py
syncr/genericfeed/admin.py
syncr/genericfeed/models.py
syncr/googlecode/__init__.py
syncr/googlecode/admin.py
syncr/googlecode/models.py
syncr/magnolia/__init__.py
syncr/magnolia/admin.py
syncr/magnolia/models.py
syncr/magnolia/pymagnolia.py
syncr/picasaweb/__init__.py
syncr/picasaweb/admin.py
syncr/picasaweb/models.py
syncr/picasaweb/management/__init__.py
syncr/picasaweb/management/commands/__init__.py
syncr/picasaweb/management/commands/sync_picasaweb.py
syncr/readernaut/__init__.py
syncr/readernaut/admin.py
syncr/readernaut/models.py
syncr/tumblr/__init__.py
syncr/tumblr/models.py
syncr/twitter/__init__.py
syncr/twitter/admin.py
syncr/twitter/models.py
syncr/twitter/templatetags/__init__.py
syncr/twitter/templatetags/twitterfy.py
syncr/youtube/__init__.py
syncr/youtube/admin.py
syncr/youtube/models.py