Metadata-Version: 1.0
Name: django-syncr
Version: 0.50
Summary: Synchronize Django with the web
Home-page: http://code.google.com/p/django-syncr
Author: Jesse Legg
Author-email: jesse.legg@gmail.com
License: UNKNOWN
Platform: UNKNOWN
Classifier: Development Status :: 3 - Alpha
Classifier: Environment :: Web Environment
Classifier: Intended Audience :: Developers
Classifier: License :: OSI Approved :: MIT License
Classifier: Operating System :: OS Independent
Classifier: Programming Language :: Python
Classifier: Framework :: Django
